asgiproxy/__init__.py
asgiproxy/__main__.py
asgiproxy/base.py
asgiproxy/config.py
asgiproxy/context.py
asgiproxy/py.typed
asgiproxy/simple_proxy.py
asgiproxy/proxies/__init__.py
asgiproxy/proxies/http.py
asgiproxy/proxies/websocket.py
asgiproxy/utils/__init__.py
asgiproxy/utils/streams.py
asgiproxy-0.1.1.dist-info/LICENSE
asgiproxy-0.1.1.dist-info/METADATA
asgiproxy-0.1.1.dist-info/WHEEL
asgiproxy-0.1.1.dist-info/top_level.txt
asgiproxy-0.1.1.dist-info/RECORD
